cursvalutarbnr.py
cursvalutarbnr-1.0.5.dist-info/licenses/LICENSE
cursvalutarbnr-1.0.5.dist-info/METADATA
cursvalutarbnr-1.0.5.dist-info/WHEEL
cursvalutarbnr-1.0.5.dist-info/top_level.txt
cursvalutarbnr-1.0.5.dist-info/RECORD
