Metadata-Version: 2.4
Name: cursvalutarbnr
Version: 1.0.5
Summary: Conversie valuta straina in lei grei
Author: Climente Alin
License-Expression: MIT
Project-URL: Homepage, https://github.com/ClimenteA/curs-valutar-bnr
Requires-Python: >=3.12
License-File: LICENSE
Requires-Dist: diskcache>=5.6.3
Requires-Dist: requests>=2.32.5
Requires-Dist: xmltodict>=1.0.2
Dynamic: license-file
